stldim/__init__.py
stldim/__main__.py
stldim/version.py
stldim/templates/openscad_lib.jinja2
stldim/templates/openscad_lib_basename.jinja2
stldim/tests/__init__.py
stldim/tests/test_mesh_with_bounds.py
stldim-0.4.2.dist-info/METADATA
stldim-0.4.2.dist-info/WHEEL
stldim-0.4.2.dist-info/entry_points.txt
stldim-0.4.2.dist-info/licenses/LICENSE.md
stldim-0.4.2.dist-info/RECORD
