Metadata-Version: 2.3
Name: stldim
Version: 0.4.2
Summary: Get dimensions of an STL file
Project-URL: Homepage, https://github.com/nomike/stldim
Project-URL: Issues, https://github.com/nomike/stldim/issues
Author-email: nomike Postmann <nomike@nomike.com>
License-File: LICENSE.md
Classifier: Development Status :: 3 - Alpha
Classifier: Environment :: Console
Classifier: Intended Audience :: Developers
Classifier: License :: OSI Approved :: MIT License
Classifier: Operating System :: OS Independent
Classifier: Programming Language :: Python :: 3
Classifier: Programming Language :: Python :: 3 :: Only
Classifier: Programming Language :: Python :: 3.8
Classifier: Programming Language :: Python :: 3.9
Classifier: Programming Language :: Python :: 3.10
Classifier: Programming Language :: Python :: 3.11
Classifier: Programming Language :: Python :: 3.12
Requires-Python: >=3.8
Requires-Dist: docopt
Requires-Dist: jinja2
Requires-Dist: numpy-stl
